pymazda/__init__.py
pymazda/client.py
pymazda/connection.py
pymazda/controller.py
pymazda/crypto_utils.py
pymazda/exceptions.py
pymazda/sensordata/__init__.py
pymazda/sensordata/android_builds.py
pymazda/sensordata/background_event_list.py
pymazda/sensordata/key_event_list.py
pymazda/sensordata/performance_test_results.py
pymazda/sensordata/sensor_data_builder.py
pymazda/sensordata/sensor_data_encryptor.py
pymazda/sensordata/sensor_data_util.py
pymazda/sensordata/system_info.py
pymazda/sensordata/touch_event_list.py
pymazda-0.3.11.dist-info/LICENSE
pymazda-0.3.11.dist-info/METADATA
pymazda-0.3.11.dist-info/WHEEL
pymazda-0.3.11.dist-info/RECORD
