Metadata-Version: 2.1
Name: pymazda
Version: 0.3.11
Summary: An API client for interacting with the MyMazda (Mazda Connected Services) API
Home-page: https://github.com/bdr99/pymazda
License: MIT
Author: Brandon Rothweiler
Author-email: brandonrothweiler@gmail.com
Requires-Python: >=3.8,<4.0
Classifier: License :: OSI Approved :: MIT License
Classifier: Operating System :: OS Independent
Classifier: Programming Language :: Python :: 3
Classifier: Programming Language :: Python :: 3.8
Classifier: Programming Language :: Python :: 3.9
Classifier: Programming Language :: Python :: 3.10
Classifier: Programming Language :: Python :: 3.11
Requires-Dist: aiohttp (>=3,<4)
Requires-Dist: cryptography (>=36.0.2)
Project-URL: Documentation, https://github.com/bdr99/pymazda
Project-URL: Repository, https://github.com/bdr99/pymazda
